gameduino2/__init__.py
gameduino2/base.py
gameduino2/convert.py
gameduino2/gd3registers.py
gameduino2/imbytes.py
gameduino2/prep.py
gameduino2/psdparser.py
gameduino2/registers.py
gameduino2/remote.py
gameduino2/tmxreader.py
gameduino2-0.4.0.data/scripts/gd2asset
gameduino2-0.4.0.data/scripts/gd3asset
gameduino2-0.4.0.dist-info/LICENSE
gameduino2-0.4.0.dist-info/METADATA
gameduino2-0.4.0.dist-info/WHEEL
gameduino2-0.4.0.dist-info/top_level.txt
gameduino2-0.4.0.dist-info/RECORD
