Metadata-Version: 2.1
Name: gameduino2
Version: 0.4.0
Summary: Package of Gameduino 2/3/3X development tools
Home-page: http://gameduino.com
Author: James Bowman
Author-email: jamesb@excamera.com
License: GPL
License-File: LICENSE
Requires-Dist: pillow
